ACKNOWLEDGEMENTS.md
CONTRIBUTING.md
LICENSE.md
MANIFEST.in
README.md
build.properties
setup.py
v1pysdk/__init__.py
v1pysdk/base_asset.py
v1pysdk/cache_decorator.py
v1pysdk/client.py
v1pysdk/none_deref.py
v1pysdk/query.py
v1pysdk/special_class_methods.py
v1pysdk/string_utils.py
v1pysdk/v1meta.py
v1pysdk/v1poll.py
v1pysdk/yamlquery.py
v1pysdk_unofficial.egg-info/PKG-INFO
v1pysdk_unofficial.egg-info/SOURCES.txt
v1pysdk_unofficial.egg-info/dependency_links.txt
v1pysdk_unofficial.egg-info/pbr.json
v1pysdk_unofficial.egg-info/requires.txt
v1pysdk_unofficial.egg-info/top_level.txt