Metadata-Version: 1.0
Name: v1pysdk-unofficial
Version: 0.4.post4
Summary: VersionOne API client
Home-page: http://github.com/VersionOne/v1pysdk
Author: Joe Koberg (VersionOne, Inc.)
Author-email: Joe.Koberg@versionone.com
License: MIT/BSD
Keywords: versionone v1 api sdk
Platform: UNKNOWN
